iimpute/__init__.py
iimpute/imputation.py
iimpute-0.1.1.dist-info/LICENSE
iimpute-0.1.1.dist-info/METADATA
iimpute-0.1.1.dist-info/WHEEL
iimpute-0.1.1.dist-info/top_level.txt
iimpute-0.1.1.dist-info/RECORD
